setup.py
dpack/__init__.py
nlplab.egg-info/PKG-INFO
nlplab.egg-info/SOURCES.txt
nlplab.egg-info/dependency_links.txt
nlplab.egg-info/requires.txt
nlplab.egg-info/top_level.txt